[
  {
    "parent": [],
    "address": "\u5fb7\u99a8\u6e90\u7b2c\u4e00\u8857",
    "distance": [],
    "pname": "\u6e56\u5357\u7701",
    "importance": [],
    "biz_ext": {
      "cost": [],
      "opentime2": "09:00-22:00",
      "rating": "4.2",
      "open_time": "09:00-22:00",
      "meal_ordering": "0"
    },
    "biz_type": "diner",
    "cityname": "\u6e58\u897f\u571f\u5bb6\u65cf\u82d7\u65cf\u81ea\u6cbb\u5dde",
    "type": "\u9910\u996e\u670d\u52a1;\u9910\u996e\u76f8\u5173\u573a\u6240;\u9910\u996e\u76f8\u5173",
    "photos": [
      {
        "title": [],
        "url": "http://s-pic.oss-cn-beijing.aliyuncs.com/desensitize/images/publish/f91f51891ab35030f8ae087f30668643.jpg"
      },
      {
        "title": [],
        "url": "http://store.is.autonavi.com/showpic/9ac6d3a9c159f5d129afb59221bf1b97"
      },
      {
        "title": [],
        "url": "http://store.is.autonavi.com/showpic/7d0b0d7e79b5d4baa73aa9dbd4472b47"
      }
    ],
    "typecode": "050000",
    "shopinfo": "0",
    "poiweight": [],
    "childtype": [],
    "adname": "\u6cf8\u6eaa\u53bf",
    "name": "luckin coffee \u745e\u5e78\u5496\u5561(\u5fb7\u99a8\u6e90\u5e97)",
    "location": "110.208299,28.215550",
    "tel": "19174389151;4000100100",
    "shopid": [],
    "id": "B0JKMSKSVJ"
  },
  {
    "parent": [],
    "address": "\u671d\u9633\u8def184\u53f7",
    "distance": [],
    "pname": "\u6e56\u5357\u7701",
    "importance": [],
    "biz_ext": {
      "cost": [],
      "opentime2": "08:30-22:00",
      "rating": "4.2",
      "open_time": "08:30-22:00",
      "meal_ordering": "0"
    },
    "biz_type": "diner",
    "cityname": "\u6e58\u897f\u571f\u5bb6\u65cf\u82d7\u65cf\u81ea\u6cbb\u5dde",
    "type": "\u9910\u996e\u670d\u52a1;\u5496\u5561\u5385;\u5496\u5561\u5385",
    "photos": [
      {
        "title": [],
        "url": "http://s-pic.oss-cn-beijing.aliyuncs.com/desensitize/images/publish/d6f450828feb4c2926ef93aeada245e1.jpg"
      },
      {
        "title": [],
        "url": "http://store.is.autonavi.com/showpic/1ec6cd0749c990ef96f9c4f077fdd5f8"
      },
      {
        "title": [],
        "url": "http://store.is.autonavi.com/showpic/d9ec9abcee56275ea7942207fd9c55ef"
      }
    ],
    "typecode": "050500",
    "shopinfo": "0",
    "poiweight": [],
    "childtype": [],
    "adname": "\u6cf8\u6eaa\u53bf",
    "name": "\u745e\u5e78\u5496\u5561Luckin coffee(\u6cf8\u6eaa\u706f\u5854\u5e97)",
    "location": "110.212264,28.215459",
    "tel": "19174383055;4000100100",
    "shopid": [],
    "id": "B0J0X7BPID"
  }
]