[
  {
    "parent": [],
    "address": "\u9149\u9633\u571f\u5bb6\u65cf\u82d7\u65cf\u81ea\u6cbb\u53bf\u5341\u5b57\u8857101\u53f7(\u65e0\u9762\u4e0d\u6b22\u897f\u4fa7)",
    "distance": [],
    "pname": "\u91cd\u5e86\u5e02",
    "importance": [],
    "biz_ext": {
      "cost": "10.00",
      "opentime2": "\u3010\u6b63\u5e38\u3011\u5168\u5e74\u5468\u4e00\u81f3\u5468\u56db08:30-21:00\uff1b\u3010\u6b63\u5e38\u3011\u5168\u5e74\u5468\u4e94\u81f3\u5468\u65e508:30-21:30",
      "rating": "3.6",
      "open_time": "08:30-21:00",
      "meal_ordering": "0"
    },
    "biz_type": "diner",
    "cityname": "\u91cd\u5e86\u5e02",
    "type": "\u9910\u996e\u670d\u52a1;\u5496\u5561\u5385;\u5496\u5561\u5385",
    "photos": [
      {
        "title": [],
        "url": "http://store.is.autonavi.com/showpic/e914601bbef5ee85069cdd95b7a9db13"
      },
      {
        "title": [],
        "url": "http://store.is.autonavi.com/showpic/9a055ade9ffc71dc2aacff89e66df583"
      },
      {
        "title": [],
        "url": "http://store.is.autonavi.com/showpic/ca49d9eda049ec5599f49e3a651460b4"
      }
    ],
    "typecode": "050500",
    "shopinfo": "1",
    "poiweight": [],
    "childtype": [],
    "adname": "\u6b66\u9686\u533a",
    "name": "\u5e93\u8fea\u5496\u5561(\u9149\u9633\u6c47\u5347\u5e7f\u573a\u5e97)",
    "location": "107.481231,29.332515",
    "tel": "18290479123",
    "shopid": [],
    "id": "B0J3MCGTXL"
  }
]