[
  {
    "parent": [],
    "address": "\u65b0\u65f6\u4ee3\u8d2d\u7269\u5e7f\u573a\u5357\u4fa7",
    "distance": [],
    "pname": "\u8fbd\u5b81\u7701",
    "importance": [],
    "biz_ext": {
      "cost": [],
      "rating": "4.5"
    },
    "biz_type": [],
    "cityname": "\u94c1\u5cad\u5e02",
    "type": "\u4f53\u80b2\u4f11\u95f2\u670d\u52a1;\u5a31\u4e50\u573a\u6240;KTV",
    "photos": [
      {
        "title": [],
        "url": "http://store.is.autonavi.com/showpic/dbc0690548e57b0406fff66e3809aff5"
      },
      {
        "title": [],
        "url": "http://store.is.autonavi.com/showpic/796202290254d06f623c7bfe3e885f1b"
      }
    ],
    "typecode": "080302",
    "shopinfo": "0",
    "poiweight": [],
    "childtype": [],
    "adname": "\u8c03\u5175\u5c71\u5e02",
    "name": "\u7d2b\u591cKTV",
    "location": "123.535621,42.429099",
    "tel": "024-76753333",
    "shopid": [],
    "id": "B0FFK1VBHN"
  },
  {
    "parent": [],
    "address": "\u8c03\u5175\u5c71\u5927\u8857\u4e0e\u91d1\u6e56\u8def\u4ea4\u53c9\u53e3\u897f\u5357140\u7c73",
    "distance": [],
    "pname": "\u8fbd\u5b81\u7701",
    "importance": [],
    "biz_ext": {
      "cost": [],
      "rating": "4.1"
    },
    "biz_type": [],
    "cityname": "\u94c1\u5cad\u5e02",
    "type": "\u4f53\u80b2\u4f11\u95f2\u670d\u52a1;\u5a31\u4e50\u573a\u6240;\u8fea\u5385",
    "photos": [
      {
        "title": [],
        "url": "http://store.is.autonavi.com/showpic/df726213202b29ae7e8c477af93ff148"
      }
    ],
    "typecode": "080303",
    "shopinfo": "0",
    "poiweight": [],
    "childtype": [],
    "adname": "\u8c03\u5175\u5c71\u5e02",
    "name": "\u6708\u4eae\u4e4b\u5149\u821e\u5385",
    "location": "123.543054,42.448825",
    "tel": [],
    "shopid": [],
    "id": "B0G1OADNCM"
  },
  {
    "parent": [],
    "address": "\u5de5\u4eba\u5927\u88573\u53f7(\u6c34\u7b19\u4f20\u5a92\u6b63\u5bf9\u9762)",
    "distance": [],
    "pname": "\u8fbd\u5b81\u7701",
    "importance": [],
    "biz_ext": {
      "cost": [],
      "rating": "4.3"
    },
    "biz_type": [],
    "cityname": "\u94c1\u5cad\u5e02",
    "type": "\u4f53\u80b2\u4f11\u95f2\u670d\u52a1;\u5a31\u4e50\u573a\u6240;KTV",
    "photos": [
      {
        "title": [],
        "url": "http://store.is.autonavi.com/showpic/a3d67c65d067aa64ad855d73415dcb92"
      },
      {
        "title": [],
        "url": "https://aos-comment.amap.com/B0J0CHDZ0O/headerImg/f2e458013e0f2d342eba1ba44ecf12e6_2048_2048_80.jpg"
      }
    ],
    "typecode": "080302",
    "shopinfo": "0",
    "poiweight": [],
    "childtype": [],
    "adname": "\u8c03\u5175\u5c71\u5e02",
    "name": "\u4e91\u5ead\u516c\u9986KTV",
    "location": "123.556911,42.439111",
    "tel": [],
    "shopid": [],
    "id": "B0J0CHDZ0O"
  },
  {
    "parent": [],
    "address": "\u7ea2\u582a\u5546\u52a1KTV",
    "distance": [],
    "pname": "\u8fbd\u5b81\u7701",
    "importance": [],
    "biz_ext": {
      "cost": [],
      "rating": "4.3"
    },
    "biz_type": [],
    "cityname": "\u94c1\u5cad\u5e02",
    "type": "\u4f53\u80b2\u4f11\u95f2\u670d\u52a1;\u5a31\u4e50\u573a\u6240;KTV",
    "photos": [
      {
        "title": [],
        "url": "http://store.is.autonavi.com/showpic/8180141820eee16aa7f0b1a9751732ba"
      },
      {
        "title": [],
        "url": "http://store.is.autonavi.com/showpic/e0e924493f6c9be077c33a6f47a979ec"
      },
      {
        "title": [],
        "url": "http://store.is.autonavi.com/showpic/eed208514649e682f965c8676cb0d361"
      }
    ],
    "typecode": "080302",
    "shopinfo": "0",
    "poiweight": [],
    "childtype": [],
    "adname": "\u8c03\u5175\u5c71\u5e02",
    "name": "\u591c\u672a\u592eKTV",
    "location": "123.547792,42.447571",
    "tel": [],
    "shopid": [],
    "id": "B0GR4MHN79"
  },
  {
    "parent": [],
    "address": "\u6708\u4eae\u6e56",
    "distance": [],
    "pname": "\u8fbd\u5b81\u7701",
    "importance": [],
    "biz_ext": {
      "cost": [],
      "rating": "4.3"
    },
    "biz_type": [],
    "cityname": "\u94c1\u5cad\u5e02",
    "type": "\u4f53\u80b2\u4f11\u95f2\u670d\u52a1;\u5a31\u4e50\u573a\u6240;KTV",
    "photos": [
      {
        "title": [],
        "url": "http://store.is.autonavi.com/showpic/ad3ce7ee4f64e2168be6391b1142e9b6"
      },
      {
        "title": [],
        "url": "http://store.is.autonavi.com/showpic/1742eb144fe36f51c34b962636e86052"
      }
    ],
    "typecode": "080302",
    "shopinfo": "0",
    "poiweight": [],
    "childtype": [],
    "adname": "\u8c03\u5175\u5c71\u5e02",
    "name": "\u91d1\u66f2",
    "location": "123.548221,42.447199",
    "tel": [],
    "shopid": [],
    "id": "B019A00EBA"
  },
  {
    "parent": [],
    "address": "\u4eff\u53e4\u8857\u4e0e\u91d1\u6e56\u8def\u4ea4\u6c47\u5904\u4e1c\u884c190\u7c73",
    "distance": [],
    "pname": "\u8fbd\u5b81\u7701",
    "importance": [],
    "biz_ext": {
      "cost": [],
      "rating": "4.1"
    },
    "biz_type": [],
    "cityname": "\u94c1\u5cad\u5e02",
    "type": "\u4f53\u80b2\u4f11\u95f2\u670d\u52a1;\u5a31\u4e50\u573a\u6240;KTV",
    "photos": [
      {
        "title": [],
        "url": "http://store.is.autonavi.com/showpic/e663f1dfd61519298aa01674086e7385"
      }
    ],
    "typecode": "080302",
    "shopinfo": "0",
    "poiweight": [],
    "childtype": [],
    "adname": "\u8c03\u5175\u5c71\u5e02",
    "name": "\u5149\u8f89\u5c81\u6708",
    "location": "123.548634,42.447398",
    "tel": [],
    "shopid": [],
    "id": "B019A0SZ2X"
  },
  {
    "parent": [],
    "address": "\u6708\u4eae\u6e56\u897f\u95e8",
    "distance": [],
    "pname": "\u8fbd\u5b81\u7701",
    "importance": [],
    "biz_ext": {
      "cost": [],
      "rating": "4.3"
    },
    "biz_type": [],
    "cityname": "\u94c1\u5cad\u5e02",
    "type": "\u4f53\u80b2\u4f11\u95f2\u670d\u52a1;\u5a31\u4e50\u573a\u6240;KTV",
    "photos": [
      {
        "title": [],
        "url": "http://store.is.autonavi.com/showpic/1b2b5d162bd9a118284cc7665e0c369e"
      },
      {
        "title": [],
        "url": "http://store.is.autonavi.com/showpic/09cf9d7ed603321274904e39224de8ee"
      },
      {
        "title": [],
        "url": "http://store.is.autonavi.com/showpic/23115bd6a69e7532ac7e6a233742c1da"
      }
    ],
    "typecode": "080302",
    "shopinfo": "0",
    "poiweight": [],
    "childtype": [],
    "adname": "\u8c03\u5175\u5c71\u5e02",
    "name": "\u591c\u98de\u884c",
    "location": "123.548457,42.447159",
    "tel": "13841019189",
    "shopid": [],
    "id": "B019A00EBD"
  },
  {
    "parent": [],
    "address": "\u516c\u5b89\u5c40\u5357\u4fa78\u53f7\u95e8\u5e02",
    "distance": [],
    "pname": "\u8fbd\u5b81\u7701",
    "importance": [],
    "biz_ext": {
      "cost": [],
      "rating": "4.3"
    },
    "biz_type": [],
    "cityname": "\u94c1\u5cad\u5e02",
    "type": "\u4f53\u80b2\u4f11\u95f2\u670d\u52a1;\u5a31\u4e50\u573a\u6240;\u9152\u5427",
    "photos": [
      {
        "title": [],
        "url": "http://store.is.autonavi.com/showpic/6437e0767e86e62ece7c48e1143677b3"
      }
    ],
    "typecode": "080304",
    "shopinfo": "0",
    "poiweight": [],
    "childtype": [],
    "adname": "\u8c03\u5175\u5c71\u5e02",
    "name": "\u6ea2\u6e90\u5c0f\u9152\u9986",
    "location": "123.548288,42.438586",
    "tel": [],
    "shopid": [],
    "id": "B0I6TRTKXF"
  },
  {
    "parent": [],
    "address": "\u8c03\u5175\u5c71\u6708\u4eae\u6e56",
    "distance": [],
    "pname": "\u8fbd\u5b81\u7701",
    "importance": [],
    "biz_ext": {
      "cost": [],
      "rating": "4.3"
    },
    "biz_type": [],
    "cityname": "\u94c1\u5cad\u5e02",
    "type": "\u4f53\u80b2\u4f11\u95f2\u670d\u52a1;\u5a31\u4e50\u573a\u6240;KTV",
    "photos": [
      {
        "title": [],
        "url": "http://store.is.autonavi.com/showpic/0d27895f6d84962547999576841f0473"
      },
      {
        "title": [],
        "url": "http://store.is.autonavi.com/showpic/2c93e19c85cefefee9cb9e76c0a4bbfe"
      },
      {
        "title": [],
        "url": "http://store.is.autonavi.com/showpic/623527ed2dbae4c15f8a8ec2a0e9ccae"
      }
    ],
    "typecode": "080302",
    "shopinfo": "0",
    "poiweight": [],
    "childtype": [],
    "adname": "\u8c03\u5175\u5c71\u5e02",
    "name": "\u7ea2\u582a\u5546\u52a1KTV",
    "location": "123.547826,42.447864",
    "tel": "024-76925888",
    "shopid": [],
    "id": "B0FFFVJRK5"
  },
  {
    "parent": [],
    "address": "\u91d1\u6e56\u8def\u4e0e\u4eff\u53e4\u8857\u4ea4\u53c9\u53e3\u4e1c\u5357240\u7c73",
    "distance": [],
    "pname": "\u8fbd\u5b81\u7701",
    "importance": [],
    "biz_ext": {
      "cost": [],
      "rating": "4.3"
    },
    "biz_type": [],
    "cityname": "\u94c1\u5cad\u5e02",
    "type": "\u4f53\u80b2\u4f11\u95f2\u670d\u52a1;\u5a31\u4e50\u573a\u6240;KTV|\u8d2d\u7269\u670d\u52a1;\u8d2d\u7269\u76f8\u5173\u573a\u6240;\u8d2d\u7269\u76f8\u5173\u573a\u6240",
    "photos": [
      {
        "title": [],
        "url": "http://store.is.autonavi.com/showpic/976fb462db47b055fd544601334951fa"
      },
      {
        "title": [],
        "url": "http://store.is.autonavi.com/showpic/6e800f6969cf81f3df1902ce440feb67"
      },
      {
        "title": [],
        "url": "http://store.is.autonavi.com/showpic/01f5ecaeedf970e0022a0574df06d5bf"
      }
    ],
    "typecode": "080302|060000",
    "shopinfo": "0",
    "poiweight": [],
    "childtype": [],
    "adname": "\u8c03\u5175\u5c71\u5e02",
    "name": "\u60c5\u6709\u72ec\u949f",
    "location": "123.548742,42.446884",
    "tel": [],
    "shopid": [],
    "id": "B019A0T0JA"
  },
  {
    "parent": "B019A05ITA",
    "address": "\u4e2d\u592e\u5927\u885716\u53f7",
    "distance": [],
    "pname": "\u8fbd\u5b81\u7701",
    "importance": [],
    "biz_ext": {
      "cost": [],
      "rating": "4.0"
    },
    "biz_type": [],
    "cityname": "\u94c1\u5cad\u5e02",
    "type": "\u4f53\u80b2\u4f11\u95f2\u670d\u52a1;\u5a31\u4e50\u573a\u6240;\u9152\u5427",
    "photos": [
      {
        "title": [],
        "url": "http://store.is.autonavi.com/showpic/28310c4447029f034eaf31ea549e9cd7"
      }
    ],
    "typecode": "080304",
    "shopinfo": "0",
    "poiweight": [],
    "childtype": "202",
    "adname": "\u8c03\u5175\u5c71\u5e02",
    "name": "\u5c71\u4e5f\u542c\u98ceBAR(\u8c03\u5175\u5c71\u5546\u4e1a\u5927\u53a6\u5e97)",
    "location": "123.551703,42.453985",
    "tel": [],
    "shopid": [],
    "id": "B0JRDAWFNF"
  },
  {
    "parent": [],
    "address": "\u6653\u5357\u9547\u5f20\u5e84",
    "distance": [],
    "pname": "\u8fbd\u5b81\u7701",
    "importance": [],
    "biz_ext": {
      "cost": [],
      "rating": "3.8"
    },
    "biz_type": [],
    "cityname": "\u94c1\u5cad\u5e02",
    "type": "\u4f53\u80b2\u4f11\u95f2\u670d\u52a1;\u5a31\u4e50\u573a\u6240;KTV",
    "photos": [
      {
        "title": [],
        "url": "http://store.is.autonavi.com/showpic/f78525011a2d44f7759e36767dbb309f"
      }
    ],
    "typecode": "080302",
    "shopinfo": "0",
    "poiweight": [],
    "childtype": [],
    "adname": "\u8c03\u5175\u5c71\u5e02",
    "name": "\u76db\u4e16\u91d1\u66f2\u6b4c\u57ce",
    "location": "123.601187,42.353802",
    "tel": "024-76769666",
    "shopid": [],
    "id": "B0FFJ938EU"
  },
  {
    "parent": [],
    "address": "\u91d1\u6e56\u8def\u4e0e\u4eff\u53e4\u8857\u4ea4\u53c9\u53e3\u4e1c\u5357100\u7c73",
    "distance": [],
    "pname": "\u8fbd\u5b81\u7701",
    "importance": [],
    "biz_ext": {
      "cost": [],
      "rating": "4.0"
    },
    "biz_type": [],
    "cityname": "\u94c1\u5cad\u5e02",
    "type": "\u4f53\u80b2\u4f11\u95f2\u670d\u52a1;\u5a31\u4e50\u573a\u6240;\u9152\u5427|\u4f53\u80b2\u4f11\u95f2\u670d\u52a1;\u5a31\u4e50\u573a\u6240;KTV",
    "photos": [
      {
        "title": [],
        "url": "http://store.is.autonavi.com/showpic/9df02b9d872d9305a61ff8abab749b01"
      },
      {
        "title": [],
        "url": "http://store.is.autonavi.com/showpic/1add0616abf6445471a329041f2c6a52"
      }
    ],
    "typecode": "080304|080302",
    "shopinfo": "0",
    "poiweight": [],
    "childtype": [],
    "adname": "\u8c03\u5175\u5c71\u5e02",
    "name": "\u5348\u591c\u55e8\u5427",
    "location": "123.547349,42.447840",
    "tel": "13008276048",
    "shopid": [],
    "id": "B019A0SJGY"
  },
  {
    "parent": [],
    "address": "\u4eff\u53e4\u8857\u4e0e\u91d1\u6e56\u8def\u4ea4\u6c47\u5904\u4e1c\u884c220\u7c73",
    "distance": [],
    "pname": "\u8fbd\u5b81\u7701",
    "importance": [],
    "biz_ext": {
      "cost": [],
      "rating": "3.7"
    },
    "biz_type": [],
    "cityname": "\u94c1\u5cad\u5e02",
    "type": "\u4f53\u80b2\u4f11\u95f2\u670d\u52a1;\u5a31\u4e50\u573a\u6240;KTV",
    "photos": [
      {
        "title": [],
        "url": "http://store.is.autonavi.com/showpic/85ab6cde52c2d9527b8f6fba26be5b0d"
      },
      {
        "title": [],
        "url": "http://store.is.autonavi.com/showpic/736690696b10e54564c311389eee2f70"
      }
    ],
    "typecode": "080302",
    "shopinfo": "0",
    "poiweight": [],
    "childtype": [],
    "adname": "\u8c03\u5175\u5c71\u5e02",
    "name": "\u7ea2\u7ee3\u697c\u6b4c\u5385",
    "location": "123.549041,42.447333",
    "tel": "15898040003",
    "shopid": [],
    "id": "B019A0SZ2V"
  },
  {
    "parent": [],
    "address": "\u73af\u5c71\u5bb6\u56ed\u4e00\u53f7\u697c",
    "distance": [],
    "pname": "\u8fbd\u5b81\u7701",
    "importance": [],
    "biz_ext": {
      "cost": [],
      "rating": "4.0"
    },
    "biz_type": [],
    "cityname": "\u94c1\u5cad\u5e02",
    "type": "\u4f53\u80b2\u4f11\u95f2\u670d\u52a1;\u5a31\u4e50\u573a\u6240;\u9152\u5427",
    "photos": [
      {
        "title": [],
        "url": "http://store.is.autonavi.com/showpic/07f05fb993971d0526b8cc2b058b820f"
      }
    ],
    "typecode": "080304",
    "shopinfo": "0",
    "poiweight": [],
    "childtype": [],
    "adname": "\u8c03\u5175\u5c71\u5e02",
    "name": "\u62c9\u9614.\u5b9d\u4e3d\u91d1Live House",
    "location": "123.537677,42.452369",
    "tel": [],
    "shopid": [],
    "id": "B0G25O0WR7"
  },
  {
    "parent": [],
    "address": "\u4e2d\u5fc3\u4e3d\u666f\u5c0f\u533aA4105\u53f7\u5546\u94fa",
    "distance": [],
    "pname": "\u8fbd\u5b81\u7701",
    "importance": [],
    "biz_ext": {
      "cost": [],
      "rating": "3.7"
    },
    "biz_type": [],
    "cityname": "\u94c1\u5cad\u5e02",
    "type": "\u4f53\u80b2\u4f11\u95f2\u670d\u52a1;\u5a31\u4e50\u573a\u6240;\u9152\u5427",
    "photos": [
      {
        "title": [],
        "url": "http://store.is.autonavi.com/showpic/626583e4e511211f69db785edbe96ca8"
      }
    ],
    "typecode": "080304",
    "shopinfo": "1",
    "poiweight": [],
    "childtype": [],
    "adname": "\u8c03\u5175\u5c71\u5e02",
    "name": "\u946b\u591c\u732b\u97f3\u4e50\u9152\u5427",
    "location": "123.547965,42.453445",
    "tel": "18698246561",
    "shopid": [],
    "id": "B0G1GAN82G"
  },
  {
    "parent": [],
    "address": "105\u7701\u9053\u5927\u660e\u5e02\u573a\u5317\u8d70100\u7c73",
    "distance": [],
    "pname": "\u8fbd\u5b81\u7701",
    "importance": [],
    "biz_ext": {
      "cost": [],
      "rating": "3.7"
    },
    "biz_type": [],
    "cityname": "\u94c1\u5cad\u5e02",
    "type": "\u4f53\u80b2\u4f11\u95f2\u670d\u52a1;\u5a31\u4e50\u573a\u6240;KTV",
    "photos": [
      {
        "title": [],
        "url": "http://store.is.autonavi.com/showpic/64d0c148dd39164844cbf766b3ac0616"
      }
    ],
    "typecode": "080302",
    "shopinfo": "0",
    "poiweight": [],
    "childtype": [],
    "adname": "\u8c03\u5175\u5c71\u5e02",
    "name": "\u97f3\u4e50\u4e4b\u58f0KTV(\u4e2d\u5171\u8c03\u5175\u5c71\u5e02\u5927\u660e\u9547\u59d4\u5458\u4f1a\u4e1c\u5317)",
    "location": "123.637436,42.541995",
    "tel": [],
    "shopid": [],
    "id": "B019A0SXKN"
  },
  {
    "parent": [],
    "address": "\u4eff\u53e4\u8857\u4e0e\u91d1\u6e56\u8def\u4ea4\u53c9\u53e3\u4e1c\u5357260\u7c73",
    "distance": [],
    "pname": "\u8fbd\u5b81\u7701",
    "importance": [],
    "biz_ext": {
      "cost": [],
      "opentime2": [],
      "rating": "4.0",
      "open_time": [],
      "meal_ordering": "0"
    },
    "biz_type": [],
    "cityname": "\u94c1\u5cad\u5e02",
    "type": "\u4f53\u80b2\u4f11\u95f2\u670d\u52a1;\u5a31\u4e50\u573a\u6240;KTV|\u9910\u996e\u670d\u52a1;\u4e2d\u9910\u5385;\u4e2d\u9910\u5385",
    "photos": [
      {
        "title": [],
        "url": "http://store.is.autonavi.com/showpic/b1e7c6750a7ae624a4f4ba842e69647c"
      },
      {
        "title": [],
        "url": "http://store.is.autonavi.com/showpic/02c99a7c87d931d4bb314834e7d5a109"
      },
      {
        "title": [],
        "url": "http://store.is.autonavi.com/showpic/0d61e9b7dc8a1019246efd023b3813c6"
      }
    ],
    "typecode": "080302|050100",
    "shopinfo": "0",
    "poiweight": [],
    "childtype": [],
    "adname": "\u8c03\u5175\u5c71\u5e02",
    "name": "\u6556\u5305\u76f8\u4f1aKTV",
    "location": "123.548548,42.446526",
    "tel": [],
    "shopid": [],
    "id": "B019A06G1P"
  },
  {
    "parent": [],
    "address": "\u8c03\u5175\u5c71\u8857\u9053\u6708\u4eae\u6e56",
    "distance": [],
    "pname": "\u8fbd\u5b81\u7701",
    "importance": [],
    "biz_ext": {
      "cost": [],
      "rating": "4.1"
    },
    "biz_type": [],
    "cityname": "\u94c1\u5cad\u5e02",
    "type": "\u4f53\u80b2\u4f11\u95f2\u670d\u52a1;\u5a31\u4e50\u573a\u6240;KTV",
    "photos": [
      {
        "title": [],
        "url": "http://store.is.autonavi.com/showpic/1d26adf3d348e43c56ce4eb3d3e3a0dd"
      }
    ],
    "typecode": "080302",
    "shopinfo": "0",
    "poiweight": [],
    "childtype": [],
    "adname": "\u8c03\u5175\u5c71\u5e02",
    "name": "\u661f\u5149\u5927\u9053(\u5409\u6e90\u5c0f\u533a\u897f)",
    "location": "123.547598,42.447997",
    "tel": [],
    "shopid": [],
    "id": "B019A0SIZW"
  },
  {
    "parent": [],
    "address": "\u6708\u4eae\u6e56",
    "distance": [],
    "pname": "\u8fbd\u5b81\u7701",
    "importance": [],
    "biz_ext": {
      "cost": [],
      "rating": "4.0"
    },
    "biz_type": [],
    "cityname": "\u94c1\u5cad\u5e02",
    "type": "\u4f53\u80b2\u4f11\u95f2\u670d\u52a1;\u5a31\u4e50\u573a\u6240;KTV",
    "photos": [
      {
        "title": [],
        "url": "http://store.is.autonavi.com/showpic/133e3368e88a4385dfe1c237ced26e99"
      }
    ],
    "typecode": "080302",
    "shopinfo": "0",
    "poiweight": [],
    "childtype": [],
    "adname": "\u8c03\u5175\u5c71\u5e02",
    "name": "\u56db\u5e73\u767d\u5929\u9e45KTV",
    "location": "123.547260,42.447754",
    "tel": [],
    "shopid": [],
    "id": "B0FFI9NYKM"
  },
  {
    "parent": [],
    "address": "\u91d1\u6e56\u8def\u4e5d\u4e5d\u7eaf\u8272\u65c1",
    "distance": [],
    "pname": "\u8fbd\u5b81\u7701",
    "importance": [],
    "biz_ext": {
      "cost": [],
      "rating": "4.0"
    },
    "biz_type": [],
    "cityname": "\u94c1\u5cad\u5e02",
    "type": "\u4f53\u80b2\u4f11\u95f2\u670d\u52a1;\u5a31\u4e50\u573a\u6240;KTV",
    "photos": [
      {
        "title": [],
        "url": "http://store.is.autonavi.com/showpic/017b0a69304c096190a3e222e10315f5"
      }
    ],
    "typecode": "080302",
    "shopinfo": "0",
    "poiweight": [],
    "childtype": [],
    "adname": "\u8c03\u5175\u5c71\u5e02",
    "name": "\u5c0f\u591c\u66f2KTV",
    "location": "123.549027,42.447255",
    "tel": [],
    "shopid": [],
    "id": "B0GR4MHUIS"
  },
  {
    "parent": [],
    "address": "\u8fce\u5bbe\u8def\u5927\u5e99\u8001\u70b8\u4e32\u65c1",
    "distance": [],
    "pname": "\u8fbd\u5b81\u7701",
    "importance": [],
    "biz_ext": {
      "cost": [],
      "rating": "3.9"
    },
    "biz_type": [],
    "cityname": "\u94c1\u5cad\u5e02",
    "type": "\u4f53\u80b2\u4f11\u95f2\u670d\u52a1;\u5a31\u4e50\u573a\u6240;KTV",
    "photos": [
      {
        "title": [],
        "url": "http://store.is.autonavi.com/showpic/cd1995784b966157ce218b817e3d1cb2"
      },
      {
        "title": [],
        "url": "http://store.is.autonavi.com/showpic/3ef7e10bce4b0323777621de0f3d7a70"
      },
      {
        "title": [],
        "url": "http://store.is.autonavi.com/showpic/b3b3dbc55cf186a23cc8bc180df90ab9"
      }
    ],
    "typecode": "080302",
    "shopinfo": "0",
    "poiweight": [],
    "childtype": [],
    "adname": "\u8c03\u5175\u5c71\u5e02",
    "name": "\u54bf\u5440\u6b4c\u57ce",
    "location": "123.537746,42.447413",
    "tel": [],
    "shopid": [],
    "id": "B019A0SYZ4"
  },
  {
    "parent": [],
    "address": "\u6708\u4eae\u6e56\u897f\u95e8\u6d1e\u9053\u535750\u7c73\u95e8\u5e02",
    "distance": [],
    "pname": "\u8fbd\u5b81\u7701",
    "importance": [],
    "biz_ext": {
      "cost": [],
      "rating": "4.1"
    },
    "biz_type": [],
    "cityname": "\u94c1\u5cad\u5e02",
    "type": "\u4f53\u80b2\u4f11\u95f2\u670d\u52a1;\u5a31\u4e50\u573a\u6240;KTV",
    "photos": [
      {
        "title": [],
        "url": "http://store.is.autonavi.com/showpic/009a5bf39d47bcd081b21589f627f0d6"
      },
      {
        "title": [],
        "url": "http://store.is.autonavi.com/showpic/623c3c4c4e2de181cb00553f421e67bf"
      },
      {
        "title": [],
        "url": "http://store.is.autonavi.com/showpic/3a1c7ea0449e56eb08ccfc8bc9143eb5"
      }
    ],
    "typecode": "080302",
    "shopinfo": "0",
    "poiweight": [],
    "childtype": [],
    "adname": "\u8c03\u5175\u5c71\u5e02",
    "name": "\u975e\u540c\u51e1\u54cdKTV",
    "location": "123.548268,42.447174",
    "tel": [],
    "shopid": [],
    "id": "B019A0SZ2N"
  },
  {
    "parent": [],
    "address": "\u4e2d\u592e\u5927\u8857",
    "distance": [],
    "pname": "\u8fbd\u5b81\u7701",
    "importance": [],
    "biz_ext": {
      "cost": [],
      "rating": "4.1"
    },
    "biz_type": [],
    "cityname": "\u94c1\u5cad\u5e02",
    "type": "\u4f53\u80b2\u4f11\u95f2\u670d\u52a1;\u5a31\u4e50\u573a\u6240;KTV",
    "photos": [
      {
        "title": [],
        "url": "http://store.is.autonavi.com/showpic/ae98122d3c7f285986cddfa8e09726b0"
      },
      {
        "title": [],
        "url": "http://store.is.autonavi.com/showpic/c0c9c8523fafe633d7fe02e4ede64b1f"
      },
      {
        "title": [],
        "url": "http://store.is.autonavi.com/showpic/e35ad304c765b7ff659c68d888a8dff1"
      }
    ],
    "typecode": "080302",
    "shopinfo": "0",
    "poiweight": [],
    "childtype": [],
    "adname": "\u8c03\u5175\u5c71\u5e02",
    "name": "\u5c0f\u7eff\u5c9b\u6b22\u5531KTV",
    "location": "123.547929,42.447514",
    "tel": [],
    "shopid": [],
    "id": "B019A05JNT"
  },
  {
    "parent": [],
    "address": "\u5140\u672f\u8857\u8857\u9053",
    "distance": [],
    "pname": "\u8fbd\u5b81\u7701",
    "importance": [],
    "biz_ext": {
      "cost": [],
      "rating": "4.0"
    },
    "biz_type": [],
    "cityname": "\u94c1\u5cad\u5e02",
    "type": "\u4f53\u80b2\u4f11\u95f2\u670d\u52a1;\u5a31\u4e50\u573a\u6240;KTV",
    "photos": [
      {
        "title": [],
        "url": "http://store.is.autonavi.com/showpic/1f24e4e20c76b59cc7fbc507f4c2e06f"
      },
      {
        "title": [],
        "url": "http://store.is.autonavi.com/showpic/5b9695be7e24e976c723aacd1b22dcc8"
      }
    ],
    "typecode": "080302",
    "shopinfo": "0",
    "poiweight": [],
    "childtype": [],
    "adname": "\u8c03\u5175\u5c71\u5e02",
    "name": "\u76db\u4e16\u6b22\u6b4c\u5a31\u4e50\u5e7f\u573a",
    "location": "123.537454,42.447553",
    "tel": [],
    "shopid": [],
    "id": "B019A06FUX"
  },
  {
    "parent": [],
    "address": "\u4e2d\u5fc3\u5c0f\u533a\u4e09\u671f\u5de5\u7a0bB\u533a\u897f\u4fa79\u53f7\u95e8\u5e02101-201",
    "distance": [],
    "pname": "\u8fbd\u5b81\u7701",
    "importance": [],
    "biz_ext": {
      "cost": [],
      "rating": "3.8"
    },
    "biz_type": [],
    "cityname": "\u94c1\u5cad\u5e02",
    "type": "\u4f53\u80b2\u4f11\u95f2\u670d\u52a1;\u5a31\u4e50\u573a\u6240;\u9152\u5427",
    "photos": [
      {
        "title": [],
        "url": "http://store.is.autonavi.com/showpic/a6f54aa78776a57039232ec3014065f4"
      },
      {
        "title": [],
        "url": "http://store.is.autonavi.com/showpic/97d3829af7c4c6e62029e3a38cc21150"
      },
      {
        "title": [],
        "url": "http://store.is.autonavi.com/showpic/aac3399c02767c9979080a3d25a26bc9"
      }
    ],
    "typecode": "080304",
    "shopinfo": "1",
    "poiweight": [],
    "childtype": [],
    "adname": "\u8c03\u5175\u5c71\u5e02",
    "name": "\u751c\u591c\u9152\u5427bar",
    "location": "123.548845,42.452776",
    "tel": "15940463150",
    "shopid": [],
    "id": "B0JG19YAZE"
  },
  {
    "parent": [],
    "address": "\u91d1\u6e56\u8def\u4e0e\u4eff\u53e4\u8857\u4ea4\u53c9\u53e3\u4e1c\u5357120\u7c73",
    "distance": [],
    "pname": "\u8fbd\u5b81\u7701",
    "importance": [],
    "biz_ext": {
      "cost": [],
      "rating": "3.8"
    },
    "biz_type": [],
    "cityname": "\u94c1\u5cad\u5e02",
    "type": "\u4f53\u80b2\u4f11\u95f2\u670d\u52a1;\u5a31\u4e50\u573a\u6240;KTV",
    "photos": [],
    "typecode": "080302",
    "shopinfo": "0",
    "poiweight": [],
    "childtype": [],
    "adname": "\u8c03\u5175\u5c71\u5e02",
    "name": "\u9ea6\u6f6eKTV",
    "location": "123.547730,42.447920",
    "tel": [],
    "shopid": [],
    "id": "B0G1PPJTCA"
  },
  {
    "parent": [],
    "address": "\u540e\u592a\u7ebf\u4e0e\u817e\u9f99\u8def\u4ea4\u53c9\u53e3\u4e1c300\u7c73",
    "distance": [],
    "pname": "\u8fbd\u5b81\u7701",
    "importance": [],
    "biz_ext": {
      "cost": [],
      "rating": "3.6"
    },
    "biz_type": [],
    "cityname": "\u94c1\u5cad\u5e02",
    "type": "\u4f53\u80b2\u4f11\u95f2\u670d\u52a1;\u5a31\u4e50\u573a\u6240;\u9152\u5427",
    "photos": [
      {
        "title": [],
        "url": "http://store.is.autonavi.com/showpic/d97e70deeff24eb62a12691cae262d04"
      }
    ],
    "typecode": "080304",
    "shopinfo": "0",
    "poiweight": [],
    "childtype": [],
    "adname": "\u8c03\u5175\u5c71\u5e02",
    "name": "\u534a\u6e7e\u97f3\u4e50\u9152\u9986",
    "location": "123.536787,42.428166",
    "tel": [],
    "shopid": [],
    "id": "B0J2C13BTT"
  },
  {
    "parent": [],
    "address": "\u91d1\u6e56\u8def21\u53f7",
    "distance": [],
    "pname": "\u8fbd\u5b81\u7701",
    "importance": [],
    "biz_ext": {
      "cost": [],
      "rating": "4.0"
    },
    "biz_type": [],
    "cityname": "\u94c1\u5cad\u5e02",
    "type": "\u4f53\u80b2\u4f11\u95f2\u670d\u52a1;\u5a31\u4e50\u573a\u6240;KTV",
    "photos": [],
    "typecode": "080302",
    "shopinfo": "0",
    "poiweight": [],
    "childtype": [],
    "adname": "\u8c03\u5175\u5c71\u5e02",
    "name": "\u541b\u60a6\u6c47KTV",
    "location": "123.547267,42.448130",
    "tel": [],
    "shopid": [],
    "id": "B0JKK7E08D"
  },
  {
    "parent": [],
    "address": "505\u56fd\u9053\u4e0e\u9547\u6822\u7ebf\u4ea4\u53c9\u53e3\u897f\u5357160\u7c73",
    "distance": [],
    "pname": "\u8fbd\u5b81\u7701",
    "importance": [],
    "biz_ext": {
      "cost": [],
      "rating": "3.3"
    },
    "biz_type": [],
    "cityname": "\u94c1\u5cad\u5e02",
    "type": "\u4f53\u80b2\u4f11\u95f2\u670d\u52a1;\u5a31\u4e50\u573a\u6240;KTV",
    "photos": [],
    "typecode": "080302",
    "shopinfo": "0",
    "poiweight": [],
    "childtype": [],
    "adname": "\u8c03\u5175\u5c71\u5e02",
    "name": "\u9ea6\u4e50\u8fea",
    "location": "123.636259,42.540473",
    "tel": [],
    "shopid": [],
    "id": "B0IATRW8D2"
  },
  {
    "parent": [],
    "address": "505\u56fd\u9053\u4e0e\u9547\u6822\u7ebf\u4ea4\u53c9\u53e3\u897f\u5357200\u7c73",
    "distance": [],
    "pname": "\u8fbd\u5b81\u7701",
    "importance": [],
    "biz_ext": {
      "cost": [],
      "rating": "3.3"
    },
    "biz_type": [],
    "cityname": "\u94c1\u5cad\u5e02",
    "type": "\u4f53\u80b2\u4f11\u95f2\u670d\u52a1;\u5a31\u4e50\u573a\u6240;KTV",
    "photos": [],
    "typecode": "080302",
    "shopinfo": "0",
    "poiweight": [],
    "childtype": [],
    "adname": "\u8c03\u5175\u5c71\u5e02",
    "name": "\u591c\u8272\u7f8eKTV",
    "location": "123.636201,42.540263",
    "tel": [],
    "shopid": [],
    "id": "B019A05GQ3"
  },
  {
    "parent": [],
    "address": "\u8fce\u5bbe\u8def\u4e0e\u73af\u5c71\u8def\u4ea4\u53c9\u53e3\u4e1c60\u7c73",
    "distance": [],
    "pname": "\u8fbd\u5b81\u7701",
    "importance": [],
    "biz_ext": {
      "cost": [],
      "rating": "1.2"
    },
    "biz_type": [],
    "cityname": "\u94c1\u5cad\u5e02",
    "type": "\u4f53\u80b2\u4f11\u95f2\u670d\u52a1;\u5a31\u4e50\u573a\u6240;\u9152\u5427",
    "photos": [],
    "typecode": "080304",
    "shopinfo": "0",
    "poiweight": [],
    "childtype": [],
    "adname": "\u8c03\u5175\u5c71\u5e02",
    "name": "\u7b49\u4f60\u5564\u9152\u5c4b",
    "location": "123.538633,42.447209",
    "tel": [],
    "shopid": [],
    "id": "B0K6AMB9PI"
  }
]