[
  {
    "parent": "B0FFKXEL31",
    "address": "\u4e1a\u5dde\u9547\u4eac\u6865\u56fd\u9645\u57ce3\u5c42",
    "distance": [],
    "pname": "\u6e56\u5317\u7701",
    "importance": [],
    "biz_ext": {
      "cost": [],
      "rating": "4.4"
    },
    "biz_type": [],
    "cityname": "\u6069\u65bd\u571f\u5bb6\u65cf\u82d7\u65cf\u81ea\u6cbb\u5dde",
    "type": "\u4f53\u80b2\u4f11\u95f2\u670d\u52a1;\u5a31\u4e50\u573a\u6240;KTV",
    "photos": [
      {
        "title": [],
        "url": "http://store.is.autonavi.com/showpic/320f3212ee9d3e69950461cb1076202a"
      },
      {
        "title": [],
        "url": "http://store.is.autonavi.com/showpic/aa77cf332e0f75122d7b17d40c0e685f"
      }
    ],
    "typecode": "080302",
    "shopinfo": "1",
    "poiweight": [],
    "childtype": "202",
    "adname": "\u5efa\u59cb\u53bf",
    "name": "\u6f6e\u6b4c\u91cf\u8d29\u5f0fKTV(\u5efa\u59cb\u5e97)",
    "location": "109.718942,30.603182",
    "tel": "0718-3235222",
    "shopid": [],
    "id": "B0FFIRTN3I"
  },
  {
    "parent": [],
    "address": "\u4e1a\u5dde\u9547\u5efa\u59cb\u5927\u9053\u957f\u5174\u4ea7\u4e1a\u57ce3\u53f7\u8def2\u53f7\u697c4\u697c",
    "distance": [],
    "pname": "\u6e56\u5317\u7701",
    "importance": [],
    "biz_ext": {
      "cost": [],
      "rating": "4.3"
    },
    "biz_type": [],
    "cityname": "\u6069\u65bd\u571f\u5bb6\u65cf\u82d7\u65cf\u81ea\u6cbb\u5dde",
    "type": "\u4f53\u80b2\u4f11\u95f2\u670d\u52a1;\u5a31\u4e50\u573a\u6240;KTV",
    "photos": [
      {
        "title": [],
        "url": "http://store.is.autonavi.com/showpic/742345c731b09b172950869fd92a5181"
      },
      {
        "title": [],
        "url": "http://store.is.autonavi.com/showpic/50021da88d47eb87e7173b3d9d16be0a"
      },
      {
        "title": [],
        "url": "http://store.is.autonavi.com/showpic/1042d1164c627e623eea9d5c08c61e63"
      }
    ],
    "typecode": "080302",
    "shopinfo": "0",
    "poiweight": [],
    "childtype": [],
    "adname": "\u5efa\u59cb\u53bf",
    "name": "\u5927\u5bcc\u8c6aKTV",
    "location": "109.740267,30.629187",
    "tel": [],
    "shopid": [],
    "id": "B0FFLJ3ADF"
  },
  {
    "parent": [],
    "address": "\u6e05\u6c5f\u5de5\u4e1a\u56ed\u8349\u5b50\u575d\u793e\u533a",
    "distance": [],
    "pname": "\u6e56\u5317\u7701",
    "importance": [],
    "biz_ext": {
      "cost": "368.00",
      "rating": "4.3"
    },
    "biz_type": [],
    "cityname": "\u6069\u65bd\u571f\u5bb6\u65cf\u82d7\u65cf\u81ea\u6cbb\u5dde",
    "type": "\u4f53\u80b2\u4f11\u95f2\u670d\u52a1;\u5a31\u4e50\u573a\u6240;KTV",
    "photos": [],
    "typecode": "080302",
    "shopinfo": "0",
    "poiweight": [],
    "childtype": [],
    "adname": "\u5efa\u59cb\u53bf",
    "name": "\u795e\u8bddKTV(\u671d\u9633\u5927\u9053\u5e97)",
    "location": "109.711133,30.597361",
    "tel": [],
    "shopid": [],
    "id": "B0FFH056T1"
  },
  {
    "parent": "B0FFG3A1BD",
    "address": "\u5e7f\u6da6\u8def29\u53f7\u4e16\u8d38\u767e\u8d27F5\u5c42",
    "distance": [],
    "pname": "\u6e56\u5317\u7701",
    "importance": [],
    "biz_ext": {
      "cost": [],
      "rating": "4.0"
    },
    "biz_type": [],
    "cityname": "\u6069\u65bd\u571f\u5bb6\u65cf\u82d7\u65cf\u81ea\u6cbb\u5dde",
    "type": "\u4f53\u80b2\u4f11\u95f2\u670d\u52a1;\u5a31\u4e50\u573a\u6240;KTV",
    "photos": [
      {
        "title": [],
        "url": "http://store.is.autonavi.com/showpic/90121bf0461b1ea7396a97282f385737"
      },
      {
        "title": [],
        "url": "http://store.is.autonavi.com/showpic/4adbba028753078489799511c0342887"
      }
    ],
    "typecode": "080302",
    "shopinfo": "0",
    "poiweight": [],
    "childtype": "202",
    "adname": "\u5efa\u59cb\u53bf",
    "name": "\u91d1\u5efa\u91cf\u8d29\u5f0fKTV(\u4e16\u8d38\u767e\u8d27\u5e97)",
    "location": "109.718264,30.599756",
    "tel": "0718-3229333",
    "shopid": [],
    "id": "B0FFJSAR8N"
  },
  {
    "parent": [],
    "address": "\u6797\u4e30\u8def",
    "distance": [],
    "pname": "\u6e56\u5317\u7701",
    "importance": [],
    "biz_ext": {
      "cost": [],
      "rating": "3.7"
    },
    "biz_type": [],
    "cityname": "\u6069\u65bd\u571f\u5bb6\u65cf\u82d7\u65cf\u81ea\u6cbb\u5dde",
    "type": "\u4f53\u80b2\u4f11\u95f2\u670d\u52a1;\u5a31\u4e50\u573a\u6240;KTV",
    "photos": [
      {
        "title": [],
        "url": "http://store.is.autonavi.com/showpic/6e281298663fb213258b2bc748c0db87"
      }
    ],
    "typecode": "080302",
    "shopinfo": "0",
    "poiweight": [],
    "childtype": [],
    "adname": "\u5efa\u59cb\u53bf",
    "name": "\u6296\u97f3\u65f6\u4ee3KTV",
    "location": "110.009835,30.451276",
    "tel": [],
    "shopid": [],
    "id": "B0H6SU0P5Y"
  },
  {
    "parent": [],
    "address": "\u8328\u6cc9\u5927\u53a6\u9644\u8fd1",
    "distance": [],
    "pname": "\u6e56\u5317\u7701",
    "importance": [],
    "biz_ext": {
      "cost": [],
      "rating": "4.0"
    },
    "biz_type": [],
    "cityname": "\u6069\u65bd\u571f\u5bb6\u65cf\u82d7\u65cf\u81ea\u6cbb\u5dde",
    "type": "\u4f53\u80b2\u4f11\u95f2\u670d\u52a1;\u5a31\u4e50\u573a\u6240;KTV",
    "photos": [
      {
        "title": [],
        "url": "http://store.is.autonavi.com/showpic/832183102ec96b8dacf9d6f2fbe2a495"
      }
    ],
    "typecode": "080302",
    "shopinfo": "0",
    "poiweight": [],
    "childtype": [],
    "adname": "\u5efa\u59cb\u53bf",
    "name": "\u8328\u6cc9\u8db3\u6d74",
    "location": "109.725181,30.602540",
    "tel": [],
    "shopid": [],
    "id": "B0FFFW23ZS"
  },
  {
    "parent": [],
    "address": "\u4e1a\u5dde\u9547\u98ce\u60c5\u88575\u53f7",
    "distance": [],
    "pname": "\u6e56\u5317\u7701",
    "importance": [],
    "biz_ext": {
      "cost": [],
      "rating": "3.9"
    },
    "biz_type": [],
    "cityname": "\u6069\u65bd\u571f\u5bb6\u65cf\u82d7\u65cf\u81ea\u6cbb\u5dde",
    "type": "\u4f53\u80b2\u4f11\u95f2\u670d\u52a1;\u5a31\u4e50\u573a\u6240;\u9152\u5427",
    "photos": [
      {
        "title": [],
        "url": "http://store.is.autonavi.com/showpic/ca125f2c80fc891a1a0b2ca9ec7c0545"
      },
      {
        "title": [],
        "url": "http://store.is.autonavi.com/showpic/4b3308c80e5c7c72021378cb51782fcb"
      }
    ],
    "typecode": "080304",
    "shopinfo": "1",
    "poiweight": [],
    "childtype": [],
    "adname": "\u5efa\u59cb\u53bf",
    "name": "\u91d1\u725b\u5ea7\u7cbe\u917f\u4ed3\u5e93\u5e97",
    "location": "109.715421,30.597767",
    "tel": "17571055175",
    "shopid": [],
    "id": "B0ID4UPXX3"
  },
  {
    "parent": [],
    "address": "\u8328\u6cc9\u8def3\u53f74\u697c",
    "distance": [],
    "pname": "\u6e56\u5317\u7701",
    "importance": [],
    "biz_ext": {
      "cost": [],
      "rating": "4.0"
    },
    "biz_type": [],
    "cityname": "\u6069\u65bd\u571f\u5bb6\u65cf\u82d7\u65cf\u81ea\u6cbb\u5dde",
    "type": "\u4f53\u80b2\u4f11\u95f2\u670d\u52a1;\u5a31\u4e50\u573a\u6240;KTV",
    "photos": [
      {
        "title": [],
        "url": "http://store.is.autonavi.com/showpic/a4fa848ed862f59e18932c846141b92d"
      }
    ],
    "typecode": "080302",
    "shopinfo": "0",
    "poiweight": [],
    "childtype": [],
    "adname": "\u5efa\u59cb\u53bf",
    "name": "\u8328\u6cc9KTV",
    "location": "109.724580,30.602203",
    "tel": [],
    "shopid": [],
    "id": "B0H2LS608E"
  },
  {
    "parent": [],
    "address": "\u666f\u9633\u5927\u9053\u4e0e\u671b\u6c5f\u8def\u4ea4\u53c9\u53e3\u897f260\u7c73",
    "distance": [],
    "pname": "\u6e56\u5317\u7701",
    "importance": [],
    "biz_ext": {
      "cost": [],
      "rating": "3.7"
    },
    "biz_type": [],
    "cityname": "\u6069\u65bd\u571f\u5bb6\u65cf\u82d7\u65cf\u81ea\u6cbb\u5dde",
    "type": "\u4f53\u80b2\u4f11\u95f2\u670d\u52a1;\u5a31\u4e50\u573a\u6240;KTV",
    "photos": [
      {
        "title": [],
        "url": "http://store.is.autonavi.com/showpic/f529523669b9cc3f1c5bb3381185b8d3"
      }
    ],
    "typecode": "080302",
    "shopinfo": "0",
    "poiweight": [],
    "childtype": [],
    "adname": "\u5efa\u59cb\u53bf",
    "name": "\u65b0\u8d77\u70b9KTV",
    "location": "109.967171,30.346768",
    "tel": [],
    "shopid": [],
    "id": "B0FFLAT07K"
  },
  {
    "parent": "B0FFG3A1BD",
    "address": "\u5e7f\u6da6\u8def29\u53f7\u6b63\u4e1c\u65b9\u541160\u7c73\u4e16\u8d38\u767e\u8d27",
    "distance": [],
    "pname": "\u6e56\u5317\u7701",
    "importance": [],
    "biz_ext": {
      "cost": [],
      "rating": "4.2"
    },
    "biz_type": [],
    "cityname": "\u6069\u65bd\u571f\u5bb6\u65cf\u82d7\u65cf\u81ea\u6cbb\u5dde",
    "type": "\u4f53\u80b2\u4f11\u95f2\u670d\u52a1;\u5a31\u4e50\u573a\u6240;KTV",
    "photos": [
      {
        "title": [],
        "url": "http://store.is.autonavi.com/showpic/c471732a1e4992dcfb7ff84224d0694f"
      }
    ],
    "typecode": "080302",
    "shopinfo": "0",
    "poiweight": [],
    "childtype": "202",
    "adname": "\u5efa\u59cb\u53bf",
    "name": "\u7199\u60a6\u4f1a\u6587\u5316\u6709\u9650\u516c\u53f8",
    "location": "109.718175,30.599650",
    "tel": [],
    "shopid": [],
    "id": "B0JG2SESU6"
  },
  {
    "parent": [],
    "address": "\u70df\u58a9\u5927\u90538\u53f7",
    "distance": [],
    "pname": "\u6e56\u5317\u7701",
    "importance": [],
    "biz_ext": {
      "cost": [],
      "rating": "4.1"
    },
    "biz_type": [],
    "cityname": "\u6069\u65bd\u571f\u5bb6\u65cf\u82d7\u65cf\u81ea\u6cbb\u5dde",
    "type": "\u4f53\u80b2\u4f11\u95f2\u670d\u52a1;\u5a31\u4e50\u573a\u6240;KTV",
    "photos": [],
    "typecode": "080302",
    "shopinfo": "0",
    "poiweight": [],
    "childtype": [],
    "adname": "\u5efa\u59cb\u53bf",
    "name": "\u4e1c\u65b9\u9b45\u529bKTV",
    "location": "109.732553,30.605687",
    "tel": "0718-3226998",
    "shopid": [],
    "id": "B0GDHUZBKC"
  },
  {
    "parent": [],
    "address": "\u9ad8\u576a\u5927\u905344\u53f7",
    "distance": [],
    "pname": "\u6e56\u5317\u7701",
    "importance": [],
    "biz_ext": {
      "cost": [],
      "rating": "3.8"
    },
    "biz_type": [],
    "cityname": "\u6069\u65bd\u571f\u5bb6\u65cf\u82d7\u65cf\u81ea\u6cbb\u5dde",
    "type": "\u4f53\u80b2\u4f11\u95f2\u670d\u52a1;\u5a31\u4e50\u573a\u6240;KTV",
    "photos": [
      {
        "title": [],
        "url": "http://store.is.autonavi.com/showpic/7df861c6740bff0fb1091d806e7bbc01"
      }
    ],
    "typecode": "080302",
    "shopinfo": "0",
    "poiweight": [],
    "childtype": [],
    "adname": "\u5efa\u59cb\u53bf",
    "name": "\u4e50\u7f8e\u6c47\u8d85\u5e02",
    "location": "110.064681,30.645859",
    "tel": "16672023222",
    "shopid": [],
    "id": "B0JRKU6GVU"
  },
  {
    "parent": [],
    "address": "\u4e1a\u5dde\u5927\u9053123-1\u53f7B1\u5c42",
    "distance": [],
    "pname": "\u6e56\u5317\u7701",
    "importance": [],
    "biz_ext": {
      "cost": [],
      "rating": "3.8"
    },
    "biz_type": [],
    "cityname": "\u6069\u65bd\u571f\u5bb6\u65cf\u82d7\u65cf\u81ea\u6cbb\u5dde",
    "type": "\u4f53\u80b2\u4f11\u95f2\u670d\u52a1;\u5a31\u4e50\u573a\u6240;KTV",
    "photos": [],
    "typecode": "080302",
    "shopinfo": "0",
    "poiweight": [],
    "childtype": [],
    "adname": "\u5efa\u59cb\u53bf",
    "name": "\u5efa\u59cb\u5bbe\u679cKTV",
    "location": "109.720448,30.600079",
    "tel": [],
    "shopid": [],
    "id": "B0JRVZNGZL"
  },
  {
    "parent": [],
    "address": "\u671d\u9633\u793e\u533a\u70df\u58a9\u5927\u9053111\u53f7",
    "distance": [],
    "pname": "\u6e56\u5317\u7701",
    "importance": [],
    "biz_ext": {
      "cost": [],
      "rating": "3.6"
    },
    "biz_type": [],
    "cityname": "\u6069\u65bd\u571f\u5bb6\u65cf\u82d7\u65cf\u81ea\u6cbb\u5dde",
    "type": "\u4f53\u80b2\u4f11\u95f2\u670d\u52a1;\u5a31\u4e50\u573a\u6240;\u9152\u5427",
    "photos": [],
    "typecode": "080304",
    "shopinfo": "0",
    "poiweight": [],
    "childtype": [],
    "adname": "\u5efa\u59cb\u53bf",
    "name": "\u5496\u8def\u9152\u5427",
    "location": "109.732302,30.596294",
    "tel": [],
    "shopid": [],
    "id": "B0JKF52LTA"
  },
  {
    "parent": [],
    "address": "\u7ea2\u571f\u4e2d\u8def\u4e0e\u7ea2\u571f\u576a\u5927\u9053\u4ea4\u53c9\u53e3\u5317120\u7c73",
    "distance": [],
    "pname": "\u6e56\u5317\u7701",
    "importance": [],
    "biz_ext": {
      "cost": [],
      "rating": "3.4"
    },
    "biz_type": [],
    "cityname": "\u6069\u65bd\u571f\u5bb6\u65cf\u82d7\u65cf\u81ea\u6cbb\u5dde",
    "type": "\u4f53\u80b2\u4f11\u95f2\u670d\u52a1;\u5a31\u4e50\u573a\u6240;\u9152\u5427",
    "photos": [],
    "typecode": "080304",
    "shopinfo": "0",
    "poiweight": [],
    "childtype": [],
    "adname": "\u5efa\u59cb\u53bf",
    "name": "\u591c\u6e2f\u9152\u9986",
    "location": "109.713614,30.603958",
    "tel": [],
    "shopid": [],
    "id": "B0GUZAFBTT"
  },
  {
    "parent": [],
    "address": "\u666f\u9633\u805a\u946b\u6c11\u5bbf\u5317\u4fa7160\u7c73",
    "distance": [],
    "pname": "\u6e56\u5317\u7701",
    "importance": [],
    "biz_ext": {
      "cost": [],
      "rating": "3.5"
    },
    "biz_type": [],
    "cityname": "\u6069\u65bd\u571f\u5bb6\u65cf\u82d7\u65cf\u81ea\u6cbb\u5dde",
    "type": "\u4f53\u80b2\u4f11\u95f2\u670d\u52a1;\u5a31\u4e50\u573a\u6240;KTV",
    "photos": [],
    "typecode": "080302",
    "shopinfo": "0",
    "poiweight": [],
    "childtype": [],
    "adname": "\u5efa\u59cb\u53bf",
    "name": "\u53d1\u6e90\u5730\u97f3\u4e50\u5427",
    "location": "109.986443,30.354261",
    "tel": "15071495000",
    "shopid": [],
    "id": "B0J1Z9I4SI"
  },
  {
    "parent": [],
    "address": "\u4e1a\u5dde\u9547\u8d22\u653f\u6240\u4e1c\u5357\u4fa7120\u7c73",
    "distance": [],
    "pname": "\u6e56\u5317\u7701",
    "importance": [],
    "biz_ext": {
      "cost": [],
      "rating": "3.6"
    },
    "biz_type": [],
    "cityname": "\u6069\u65bd\u571f\u5bb6\u65cf\u82d7\u65cf\u81ea\u6cbb\u5dde",
    "type": "\u4f53\u80b2\u4f11\u95f2\u670d\u52a1;\u5a31\u4e50\u573a\u6240;KTV",
    "photos": [],
    "typecode": "080302",
    "shopinfo": "0",
    "poiweight": [],
    "childtype": [],
    "adname": "\u5efa\u59cb\u53bf",
    "name": "\u4e9a\u9f99KTV",
    "location": "109.729399,30.612327",
    "tel": [],
    "shopid": [],
    "id": "B0I1LDMC5L"
  },
  {
    "parent": [],
    "address": "\u70df\u58a9\u5927\u9053\u4e0e\u5c0f\u6cb3\u8fb9\u4e00\u8857\u4ea4\u53c9\u53e3\u897f\u5357120\u7c73",
    "distance": [],
    "pname": "\u6e56\u5317\u7701",
    "importance": [],
    "biz_ext": {
      "cost": [],
      "rating": "3.7"
    },
    "biz_type": [],
    "cityname": "\u6069\u65bd\u571f\u5bb6\u65cf\u82d7\u65cf\u81ea\u6cbb\u5dde",
    "type": "\u4f53\u80b2\u4f11\u95f2\u670d\u52a1;\u5a31\u4e50\u573a\u6240;\u9152\u5427",
    "photos": [],
    "typecode": "080304",
    "shopinfo": "0",
    "poiweight": [],
    "childtype": [],
    "adname": "\u5efa\u59cb\u53bf",
    "name": "\u5496\u8def\u9152\u5427",
    "location": "109.731991,30.596737",
    "tel": [],
    "shopid": [],
    "id": "B0JKHB5Y2D"
  },
  {
    "parent": [],
    "address": "\u6cbf\u6cb3\u8def1\u53f7",
    "distance": [],
    "pname": "\u6e56\u5317\u7701",
    "importance": [],
    "biz_ext": {
      "cost": [],
      "rating": "3.7"
    },
    "biz_type": [],
    "cityname": "\u6069\u65bd\u571f\u5bb6\u65cf\u82d7\u65cf\u81ea\u6cbb\u5dde",
    "type": "\u4f53\u80b2\u4f11\u95f2\u670d\u52a1;\u5a31\u4e50\u573a\u6240;KTV",
    "photos": [],
    "typecode": "080302",
    "shopinfo": "0",
    "poiweight": [],
    "childtype": [],
    "adname": "\u5efa\u59cb\u53bf",
    "name": "\u591c\u660e\u73e0",
    "location": "109.721077,30.598182",
    "tel": [],
    "shopid": [],
    "id": "B0JU3Z15TH"
  },
  {
    "parent": [],
    "address": "\u9ad8\u576a\u9547\u8d22\u653f\u6240\u5357\u4fa790\u7c73",
    "distance": [],
    "pname": "\u6e56\u5317\u7701",
    "importance": [],
    "biz_ext": {
      "cost": [],
      "opentime2": [],
      "rating": "3.3",
      "open_time": [],
      "meal_ordering": "0"
    },
    "biz_type": [],
    "cityname": "\u6069\u65bd\u571f\u5bb6\u65cf\u82d7\u65cf\u81ea\u6cbb\u5dde",
    "type": "\u4f53\u80b2\u4f11\u95f2\u670d\u52a1;\u5a31\u4e50\u573a\u6240;\u9152\u5427|\u9910\u996e\u670d\u52a1;\u4e2d\u9910\u5385;\u4e2d\u9910\u5385",
    "photos": [],
    "typecode": "080304|050100",
    "shopinfo": "0",
    "poiweight": [],
    "childtype": [],
    "adname": "\u5efa\u59cb\u53bf",
    "name": "\u4f17\u4e8c\u9152\u9986(\u5730\u5fc3\u8c37\u5e97)",
    "location": "110.067619,30.652000",
    "tel": [],
    "shopid": [],
    "id": "B0J2ZZDQL9"
  }
]