[
  {
    "parent": [],
    "address": "\u5149\u660e\u5c0f\u533a\u5341\u5b57\u8def\u53e3",
    "distance": [],
    "pname": "\u65b0\u7586\u7ef4\u543e\u5c14\u81ea\u6cbb\u533a",
    "importance": [],
    "biz_ext": {
      "cost": [],
      "opentime2": "07:00-15:00",
      "rating": "4.1",
      "open_time": "07:00-15:00",
      "meal_ordering": "0"
    },
    "biz_type": "diner",
    "cityname": "\u5580\u4ec0\u5730\u533a",
    "type": "\u9910\u996e\u670d\u52a1;\u5feb\u9910\u5385;\u5feb\u9910\u5385",
    "photos": [
      {
        "title": [],
        "url": "http://store.is.autonavi.com/showpic/c68edbf82ab7b9b9131185d53bb980d0"
      }
    ],
    "typecode": "050300",
    "shopinfo": "1",
    "poiweight": [],
    "childtype": [],
    "adname": "\u82f1\u5409\u6c99\u53bf",
    "name": "\u997c\u7231\u7ca5\u65e9\u9910\u5e97",
    "location": "76.165424,38.944269",
    "tel": "15026313993",
    "shopid": [],
    "id": "B0FFKYLL5U"
  },
  {
    "parent": "B0IRXZYOG2",
    "address": "\u534e\u65b0\u516c\u99862\u53f7\u697c9\u53f7\u5546\u94fa",
    "distance": [],
    "pname": "\u65b0\u7586\u7ef4\u543e\u5c14\u81ea\u6cbb\u533a",
    "importance": [],
    "biz_ext": {
      "cost": [],
      "opentime2": "08:00-24:00",
      "rating": "4.0",
      "open_time": "08:00-24:00",
      "meal_ordering": "0"
    },
    "biz_type": "diner",
    "cityname": "\u5580\u4ec0\u5730\u533a",
    "type": "\u9910\u996e\u670d\u52a1;\u5feb\u9910\u5385;\u5feb\u9910\u5385",
    "photos": [
      {
        "title": [],
        "url": "http://store.is.autonavi.com/showpic/8bd17631105720906239547195856669"
      },
      {
        "title": [],
        "url": "http://store.is.autonavi.com/showpic/396489520f0e581e51a8341c9bf60c72"
      },
      {
        "title": [],
        "url": "http://store.is.autonavi.com/showpic/ccded5badec944078e1018e2401ffe93"
      }
    ],
    "typecode": "050300",
    "shopinfo": "1",
    "poiweight": [],
    "childtype": "320",
    "adname": "\u82f1\u5409\u6c99\u53bf",
    "name": "\u820c\u5c16\u5c16\u5170\u5dde\u725b\u8089\u9762(\u534e\u65b0\u516c\u9986\u5e97)",
    "location": "76.181259,38.944452",
    "tel": "13058763119",
    "shopid": [],
    "id": "B0JROR3WG6"
  },
  {
    "parent": [],
    "address": "\u65b0\u5e02\u8def28\u53f7\u76db\u5143\u5927\u9152\u5e97\u4e8c\u5c42\u53f3\u4fa7",
    "distance": [],
    "pname": "\u65b0\u7586\u7ef4\u543e\u5c14\u81ea\u6cbb\u533a",
    "importance": [],
    "biz_ext": {
      "cost": [],
      "opentime2": "18:00-07:00",
      "rating": "4.0",
      "open_time": "18:00-07:00",
      "meal_ordering": "0"
    },
    "biz_type": "diner",
    "cityname": "\u5580\u4ec0\u5730\u533a",
    "type": "\u9910\u996e\u670d\u52a1;\u5feb\u9910\u5385;\u5feb\u9910\u5385",
    "photos": [
      {
        "title": [],
        "url": "http://store.is.autonavi.com/query_pic?id=stb5f016aa-28f1-4b66-9adb-08d7996ef4d2&user=search&operate=original"
      },
      {
        "title": [],
        "url": "http://store.is.autonavi.com/showpic/efc5971d22a88d238e57b8c73c1cd263"
      },
      {
        "title": [],
        "url": "https://comment-oss-online.oss-cn-wulanchabu.aliyuncs.com/B0IDPRQI2L/headerImg/content_media_external_images_media_464_1652882938122_f4d8fa18.jpg"
      }
    ],
    "typecode": "050300",
    "shopinfo": "1",
    "poiweight": [],
    "childtype": [],
    "adname": "\u82f1\u5409\u6c99\u53bf",
    "name": "\u6d3e\u4e50\u6c49\u5821\u00b7\u70b8\u9e21(\u7f8e\u98df\u8857\u5e97)",
    "location": "76.172148,38.938266",
    "tel": "15599921116",
    "shopid": [],
    "id": "B0IDPRQI2L"
  },
  {
    "parent": "B03E60MV29",
    "address": "\u4e54\u52d2\u6f58\u8def\u4e0e\u65b0\u5e02\u8def\u4ea4\u53c9\u53e3\u5317380\u7c73",
    "distance": [],
    "pname": "\u65b0\u7586\u7ef4\u543e\u5c14\u81ea\u6cbb\u533a",
    "importance": [],
    "biz_ext": {
      "cost": [],
      "opentime2": [],
      "rating": "4.0",
      "open_time": [],
      "meal_ordering": "0"
    },
    "biz_type": "diner",
    "cityname": "\u5580\u4ec0\u5730\u533a",
    "type": "\u9910\u996e\u670d\u52a1;\u5feb\u9910\u5385;\u5feb\u9910\u5385",
    "photos": [],
    "typecode": "050300",
    "shopinfo": "0",
    "poiweight": [],
    "childtype": "320",
    "adname": "\u82f1\u5409\u6c99\u53bf",
    "name": "\u5e7a\u59b9\u9762\u9986(\u82f1\u5409\u6c99\u53bf\u6ee8\u6e56\u82b1\u56ed\u5c0f\u533a\u5e97)",
    "location": "76.171263,38.942240",
    "tel": "18299866564",
    "shopid": [],
    "id": "B0HKDUZ8QP"
  },
  {
    "parent": [],
    "address": "\u65b0\u5e02\u8def79\u53f7",
    "distance": [],
    "pname": "\u65b0\u7586\u7ef4\u543e\u5c14\u81ea\u6cbb\u533a",
    "importance": [],
    "biz_ext": {
      "cost": [],
      "opentime2": "11:00-23:00",
      "rating": "4.1",
      "open_time": "11:00-23:00",
      "meal_ordering": "0"
    },
    "biz_type": "diner",
    "cityname": "\u5580\u4ec0\u5730\u533a",
    "type": "\u9910\u996e\u670d\u52a1;\u5feb\u9910\u5385;\u5feb\u9910\u5385",
    "photos": [
      {
        "title": [],
        "url": "http://store.is.autonavi.com/query_pic?id=st731d41b4-b866-4646-bc9e-3487860842fa&user=search&operate=original"
      },
      {
        "title": [],
        "url": "http://s-pic.oss-cn-beijing.aliyuncs.com/desensitize/images/publish/7a25e3b114087621ec0092a4d4d6d1e1.jpg"
      },
      {
        "title": [],
        "url": "http://store.is.autonavi.com/showpic/51535ee66d62691cd8cdaa9a0e3b7b1e"
      }
    ],
    "typecode": "050300",
    "shopinfo": "0",
    "poiweight": [],
    "childtype": [],
    "adname": "\u82f1\u5409\u6c99\u53bf",
    "name": "\u8d1d\u514b\u6c49\u5821(\u65b0\u5e02\u8def\u5e97)",
    "location": "76.171597,38.935848",
    "tel": "17699968666",
    "shopid": [],
    "id": "B0IDB5NEW3"
  },
  {
    "parent": [],
    "address": "\u8292\u8f9b\u8def\u4e0e\u514b\u5b5c\u52d2\u8def\u4ea4\u53c9\u53e3\u897f260\u7c73",
    "distance": [],
    "pname": "\u65b0\u7586\u7ef4\u543e\u5c14\u81ea\u6cbb\u533a",
    "importance": [],
    "biz_ext": {
      "cost": [],
      "opentime2": [],
      "rating": "3.9",
      "open_time": [],
      "meal_ordering": "0"
    },
    "biz_type": "diner",
    "cityname": "\u5580\u4ec0\u5730\u533a",
    "type": "\u9910\u996e\u670d\u52a1;\u5feb\u9910\u5385;\u5feb\u9910\u5385",
    "photos": [
      {
        "title": [],
        "url": "http://store.is.autonavi.com/showpic/3ca5c9c8dcbd81ae31e839e7daa271e0"
      }
    ],
    "typecode": "050300",
    "shopinfo": "0",
    "poiweight": [],
    "childtype": [],
    "adname": "\u82f1\u5409\u6c99\u53bf",
    "name": "\u7ea2\u6a31\u6843\u5feb\u9910\u5e97",
    "location": "76.174312,38.929025",
    "tel": [],
    "shopid": [],
    "id": "B0JRD590I9"
  },
  {
    "parent": [],
    "address": "\u8272\u63d0\u529b\u8def\u4e0e\u8292\u8f9b\u8def\u4ea4\u53c9\u53e3\u5317120\u7c73",
    "distance": [],
    "pname": "\u65b0\u7586\u7ef4\u543e\u5c14\u81ea\u6cbb\u533a",
    "importance": [],
    "biz_ext": {
      "cost": [],
      "opentime2": "09:00-23:30",
      "rating": "3.9",
      "open_time": "09:00-23:30",
      "meal_ordering": "0"
    },
    "biz_type": "diner",
    "cityname": "\u5580\u4ec0\u5730\u533a",
    "type": "\u9910\u996e\u670d\u52a1;\u5feb\u9910\u5385;\u5feb\u9910\u5385",
    "photos": [
      {
        "title": [],
        "url": "http://store.is.autonavi.com/showpic/becebf49273e7776a7981664f1e331c2"
      }
    ],
    "typecode": "050300",
    "shopinfo": "0",
    "poiweight": [],
    "childtype": [],
    "adname": "\u82f1\u5409\u6c99\u53bf",
    "name": "\u5343\u91cc\u9999\u56de\u65cf\u725b\u8089\u9762",
    "location": "76.177256,38.930395",
    "tel": [],
    "shopid": [],
    "id": "B0G0KOWL27"
  },
  {
    "parent": "B0FFH0GBB0",
    "address": "\u65b0\u5e02\u8def64\u53f7\u82f1\u5409\u6c99\u53bf\u6b65\u884c\u8857",
    "distance": [],
    "pname": "\u65b0\u7586\u7ef4\u543e\u5c14\u81ea\u6cbb\u533a",
    "importance": [],
    "biz_ext": {
      "cost": [],
      "opentime2": "08:00-23:00",
      "rating": "3.8",
      "open_time": "08:00-23:00",
      "meal_ordering": "0"
    },
    "biz_type": "diner",
    "cityname": "\u5580\u4ec0\u5730\u533a",
    "type": "\u9910\u996e\u670d\u52a1;\u5feb\u9910\u5385;\u5feb\u9910\u5385",
    "photos": [
      {
        "title": [],
        "url": "http://store.is.autonavi.com/showpic/2156268eb8d73374cf958b1f9619f75e"
      },
      {
        "title": [],
        "url": "http://store.is.autonavi.com/showpic/174abae3ffd68e6d40c9f1aa8eff1566"
      }
    ],
    "typecode": "050300",
    "shopinfo": "1",
    "poiweight": [],
    "childtype": "324",
    "adname": "\u82f1\u5409\u6c99\u53bf",
    "name": "\u4e09\u79e6\u7f50\u7f50\u997a\u5b50",
    "location": "76.172289,38.935417",
    "tel": "15739956628",
    "shopid": [],
    "id": "B0HKYHUZ3F"
  },
  {
    "parent": [],
    "address": "\u5e78\u798f\u8def\u4e0e194\u4e61\u9053\u4ea4\u53c9\u53e3\u4e1c400\u7c73",
    "distance": [],
    "pname": "\u65b0\u7586\u7ef4\u543e\u5c14\u81ea\u6cbb\u533a",
    "importance": [],
    "biz_ext": {
      "cost": [],
      "opentime2": [],
      "rating": "3.9",
      "open_time": [],
      "meal_ordering": "0"
    },
    "biz_type": "diner",
    "cityname": "\u5580\u4ec0\u5730\u533a",
    "type": "\u9910\u996e\u670d\u52a1;\u5feb\u9910\u5385;\u5feb\u9910\u5385",
    "photos": [],
    "typecode": "050300",
    "shopinfo": "0",
    "poiweight": [],
    "childtype": [],
    "adname": "\u82f1\u5409\u6c99\u53bf",
    "name": "\u674e\u54e5\u9c9c\u5305",
    "location": "76.167539,38.949008",
    "tel": "18209983986",
    "shopid": [],
    "id": "B0JUUSH13F"
  },
  {
    "parent": [],
    "address": "\u5149\u660e\u8def",
    "distance": [],
    "pname": "\u65b0\u7586\u7ef4\u543e\u5c14\u81ea\u6cbb\u533a",
    "importance": [],
    "biz_ext": {
      "cost": [],
      "opentime2": "08:00-23:00",
      "rating": "3.6",
      "open_time": "08:00-23:00",
      "meal_ordering": "0"
    },
    "biz_type": "diner",
    "cityname": "\u5580\u4ec0\u5730\u533a",
    "type": "\u9910\u996e\u670d\u52a1;\u5feb\u9910\u5385;\u5feb\u9910\u5385",
    "photos": [
      {
        "title": [],
        "url": "http://store.is.autonavi.com/showpic/17a8d6d4ddbc7dd4638c1a49dc7296fb"
      }
    ],
    "typecode": "050300",
    "shopinfo": "1",
    "poiweight": [],
    "childtype": [],
    "adname": "\u82f1\u5409\u6c99\u53bf",
    "name": "\u8001\u9762\u9992\u5934",
    "location": "76.165090,38.945119",
    "tel": "15894030168",
    "shopid": [],
    "id": "B0JR4H9I1U"
  },
  {
    "parent": [],
    "address": "\u82f1\u4e5f\u5c14\u8def\u4e0e\u65b0\u5e02\u8def\u4ea4\u53c9\u53e3\u4e1c160\u7c73",
    "distance": [],
    "pname": "\u65b0\u7586\u7ef4\u543e\u5c14\u81ea\u6cbb\u533a",
    "importance": [],
    "biz_ext": {
      "cost": [],
      "opentime2": "11:00-23:30",
      "rating": "3.7",
      "open_time": "11:00-23:30",
      "meal_ordering": "0"
    },
    "biz_type": "diner",
    "cityname": "\u5580\u4ec0\u5730\u533a",
    "type": "\u9910\u996e\u670d\u52a1;\u5feb\u9910\u5385;\u5feb\u9910\u5385",
    "photos": [],
    "typecode": "050300",
    "shopinfo": "0",
    "poiweight": [],
    "childtype": [],
    "adname": "\u82f1\u5409\u6c99\u53bf",
    "name": "\u82f1\u5409\u6c99\u53bf\u7279\u5236\u5927\u6392\u9762",
    "location": "76.172986,38.934107",
    "tel": [],
    "shopid": [],
    "id": "B0HKMRDT4T"
  },
  {
    "parent": [],
    "address": "\u827e\u53e4\u65af\u8def\u4e0e\u9f99\u752b\u8def\u4ea4\u53c9\u53e3\u897f60\u7c73",
    "distance": [],
    "pname": "\u65b0\u7586\u7ef4\u543e\u5c14\u81ea\u6cbb\u533a",
    "importance": [],
    "biz_ext": {
      "cost": [],
      "opentime2": [],
      "rating": "3.6",
      "open_time": [],
      "meal_ordering": "0"
    },
    "biz_type": "diner",
    "cityname": "\u5580\u4ec0\u5730\u533a",
    "type": "\u9910\u996e\u670d\u52a1;\u5feb\u9910\u5385;\u5feb\u9910\u5385",
    "photos": [
      {
        "title": [],
        "url": "http://store.is.autonavi.com/showpic/37e3a7b3bfdd7e8b7fc54b0091e06dc1"
      },
      {
        "title": [],
        "url": "http://store.is.autonavi.com/showpic/6402a350dd5948e2f17bb9bd3b4084df"
      }
    ],
    "typecode": "050300",
    "shopinfo": "1",
    "poiweight": [],
    "childtype": [],
    "adname": "\u82f1\u5409\u6c99\u53bf",
    "name": "\u82f1\u5409\u6c99\u53bfWo You\u725b\u8089\u9762\u9986",
    "location": "76.164284,38.930137",
    "tel": [],
    "shopid": [],
    "id": "B0J1PZYVKI"
  },
  {
    "parent": [],
    "address": "\u76f8\u4fe1\u6c7d\u8f66\u7535\u8def\u7ef4\u4fee\u4fdd\u517b\u4e2d\u5fc3\u5317\u4fa760\u7c73",
    "distance": [],
    "pname": "\u65b0\u7586\u7ef4\u543e\u5c14\u81ea\u6cbb\u533a",
    "importance": [],
    "biz_ext": {
      "cost": [],
      "opentime2": [],
      "rating": "3.6",
      "open_time": [],
      "meal_ordering": "0"
    },
    "biz_type": "diner",
    "cityname": "\u5580\u4ec0\u5730\u533a",
    "type": "\u9910\u996e\u670d\u52a1;\u5feb\u9910\u5385;\u8336\u9910\u5385",
    "photos": [
      {
        "title": [],
        "url": "http://store.is.autonavi.com/showpic/b234090db5b5cd006c857a104c96c463"
      }
    ],
    "typecode": "050305",
    "shopinfo": "0",
    "poiweight": [],
    "childtype": [],
    "adname": "\u82f1\u5409\u6c99\u53bf",
    "name": "\u6c11\u77e5\u8336\u9910\u5385",
    "location": "76.182992,38.948059",
    "tel": [],
    "shopid": [],
    "id": "B0GRV5TIN7"
  },
  {
    "parent": [],
    "address": "\u9f99\u752b\u8def2\u7ec4101\u53f7\u9644001\u53f7",
    "distance": [],
    "pname": "\u65b0\u7586\u7ef4\u543e\u5c14\u81ea\u6cbb\u533a",
    "importance": [],
    "biz_ext": {
      "cost": [],
      "opentime2": "\u6bcf\u592911:00-23:50",
      "rating": "3.9",
      "open_time": "11:00-23:50",
      "meal_ordering": "0"
    },
    "biz_type": "diner",
    "cityname": "\u5580\u4ec0\u5730\u533a",
    "type": "\u9910\u996e\u670d\u52a1;\u5feb\u9910\u5385;\u5feb\u9910\u5385",
    "photos": [
      {
        "title": [],
        "url": "http://store.is.autonavi.com/showpic/94f7424dd289c4fa0cec270ed0eb754c"
      },
      {
        "title": [],
        "url": "http://store.is.autonavi.com/showpic/b658aaba5edf941bdab8942c55eeb4ca"
      },
      {
        "title": [],
        "url": "http://store.is.autonavi.com/showpic/2a10df4cc59f378dea17cbd08406ac4a"
      }
    ],
    "typecode": "050300",
    "shopinfo": "1",
    "poiweight": [],
    "childtype": [],
    "adname": "\u82f1\u5409\u6c99\u53bf",
    "name": "\u9700\u8981\u54aa\u706b\u5e72\u9505\u996e\u98df\u57ce",
    "location": "76.164520,38.928701",
    "tel": "16699999829",
    "shopid": [],
    "id": "B0FFKY8UJL"
  },
  {
    "parent": [],
    "address": "\u82f1\u5409\u6c99\u4e8c\u5c0f\u5317\u4fa7130\u7c73",
    "distance": [],
    "pname": "\u65b0\u7586\u7ef4\u543e\u5c14\u81ea\u6cbb\u533a",
    "importance": [],
    "biz_ext": {
      "cost": [],
      "opentime2": "10:00-23:00",
      "rating": "2.9",
      "open_time": "10:00-23:00",
      "meal_ordering": "0"
    },
    "biz_type": "diner",
    "cityname": "\u5580\u4ec0\u5730\u533a",
    "type": "\u9910\u996e\u670d\u52a1;\u5feb\u9910\u5385;\u5feb\u9910\u5385",
    "photos": [
      {
        "title": [],
        "url": "http://store.is.autonavi.com/showpic/93398e59fbe8e10112f22d4e7f433bdc"
      }
    ],
    "typecode": "050300",
    "shopinfo": "0",
    "poiweight": [],
    "childtype": [],
    "adname": "\u82f1\u5409\u6c99\u53bf",
    "name": "\u6b63\u65b0\u9e21\u6392(\u8292\u8f9b\u8def\u5e97)",
    "location": "76.174326,38.929110",
    "tel": "4008218566",
    "shopid": [],
    "id": "B0GRVRUNHK"
  },
  {
    "parent": "B0GRJCMN8Z",
    "address": "\u57ce\u9547\u82b1\u56ed\u8def",
    "distance": [],
    "pname": "\u65b0\u7586\u7ef4\u543e\u5c14\u81ea\u6cbb\u533a",
    "importance": [],
    "biz_ext": {
      "cost": [],
      "opentime2": "11:00-00:30",
      "rating": "3.7",
      "open_time": "11:00-00:30",
      "meal_ordering": "0"
    },
    "biz_type": "diner",
    "cityname": "\u5580\u4ec0\u5730\u533a",
    "type": "\u9910\u996e\u670d\u52a1;\u5feb\u9910\u5385;\u5feb\u9910\u5385",
    "photos": [
      {
        "title": [],
        "url": "http://store.is.autonavi.com/showpic/8b5041e7e704c35d1d136950dbee08f3"
      }
    ],
    "typecode": "050300",
    "shopinfo": "1",
    "poiweight": [],
    "childtype": "324",
    "adname": "\u82f1\u5409\u6c99\u53bf",
    "name": "\u827e\u5c3c\u4e73\u9e3d",
    "location": "76.170356,38.926571",
    "tel": "17899267842",
    "shopid": [],
    "id": "B0HDZ505QG"
  },
  {
    "parent": [],
    "address": "\u82f1\u4e5f\u5c14\u8def\u4e0e\u65b0\u5e02\u8def\u4ea4\u53c9\u53e3\u4e1c\u5317140\u7c73",
    "distance": [],
    "pname": "\u65b0\u7586\u7ef4\u543e\u5c14\u81ea\u6cbb\u533a",
    "importance": [],
    "biz_ext": {
      "cost": [],
      "opentime2": [],
      "rating": "2.9",
      "open_time": [],
      "meal_ordering": "0"
    },
    "biz_type": "diner",
    "cityname": "\u5580\u4ec0\u5730\u533a",
    "type": "\u9910\u996e\u670d\u52a1;\u5feb\u9910\u5385;\u5feb\u9910\u5385",
    "photos": [],
    "typecode": "050300",
    "shopinfo": "0",
    "poiweight": [],
    "childtype": [],
    "adname": "\u82f1\u5409\u6c99\u53bf",
    "name": "\u5c0f\u98df\u4ee3(\u82f1\u4e5f\u5c14\u8def\u5e97)",
    "location": "76.172657,38.934247",
    "tel": [],
    "shopid": [],
    "id": "B0ID7UANRT"
  },
  {
    "parent": [],
    "address": "\u65b0\u5e02\u8def\u4e0e\u82f1\u4e5f\u5c14\u8def\u4ea4\u53c9\u53e3\u5317220\u7c73",
    "distance": [],
    "pname": "\u65b0\u7586\u7ef4\u543e\u5c14\u81ea\u6cbb\u533a",
    "importance": [],
    "biz_ext": {
      "cost": [],
      "opentime2": [],
      "rating": "1.9",
      "open_time": [],
      "meal_ordering": "0"
    },
    "biz_type": "diner",
    "cityname": "\u5580\u4ec0\u5730\u533a",
    "type": "\u9910\u996e\u670d\u52a1;\u5feb\u9910\u5385;\u5feb\u9910\u5385",
    "photos": [],
    "typecode": "050300",
    "shopinfo": "0",
    "poiweight": [],
    "childtype": [],
    "adname": "\u82f1\u5409\u6c99\u53bf",
    "name": "\u597d\u8d77\u70b9\u65e9\u9910\u5e97",
    "location": "76.171871,38.935427",
    "tel": [],
    "shopid": [],
    "id": "B0ID77LHS5"
  }
]